sierpinski_hpo/__init__.py
sierpinski_hpo/hpo.py
sierpinski_hpo-0.1.0.dist-info/LICENSE
sierpinski_hpo-0.1.0.dist-info/METADATA
sierpinski_hpo-0.1.0.dist-info/WHEEL
sierpinski_hpo-0.1.0.dist-info/top_level.txt
sierpinski_hpo-0.1.0.dist-info/RECORD
