Metadata-Version: 2.2
Name: sierpinski_hpo
Version: 0.1.0
Summary: A Sierpinski Triangle-based Hyperparameter Optimization algorithm.
Author: Abhishek Pandey
Classifier: Programming Language :: Python :: 3
Classifier: License :: OSI Approved :: MIT License
Classifier: Operating System :: OS Independent
Requires-Python: >=3.6
License-File: LICENSE
Requires-Dist: numpy
Requires-Dist: matplotlib
Requires-Dist: scipy
Dynamic: author
Dynamic: classifier
Dynamic: requires-dist
Dynamic: requires-python
Dynamic: summary
